antibody_ngs_pipeline/__init__.py
antibody_ngs_pipeline/config.py
antibody_ngs_pipeline/horseshoe.py
antibody_ngs_pipeline/seaside_reef.py
antibody_ngs_pipeline-1.0.3.dev0.data/scripts/antibody_ngs_pipeline
antibody_ngs_pipeline-1.0.3.dev0.dist-info/DESCRIPTION.rst
antibody_ngs_pipeline-1.0.3.dev0.dist-info/METADATA
antibody_ngs_pipeline-1.0.3.dev0.dist-info/RECORD
antibody_ngs_pipeline-1.0.3.dev0.dist-info/WHEEL
antibody_ngs_pipeline-1.0.3.dev0.dist-info/metadata.json
antibody_ngs_pipeline-1.0.3.dev0.dist-info/top_level.txt
bin/__init__.py
