Metadata-Version: 2.0
Name: antibody-ngs-pipeline
Version: 1.0.3.dev0
Summary: Bulk antibody sequence preprocessing, annotation with abstar, upload to MongoDB and S3
Home-page: https://www.github.com/CollinJ0/antibody_ngs_pipeline
Author: CollinJ0
License: UNKNOWN
Platform: UNKNOWN
Classifier: Programming Language :: Python :: 3
Classifier: License :: OSI Approved :: MIT License
Classifier: Operating System :: OS Independent
